jaane/__init__.py
jaane/jaane.py
jaane-0.1.1.dist-info/licenses/LICENCE
jaane-0.1.1.dist-info/METADATA
jaane-0.1.1.dist-info/WHEEL
jaane-0.1.1.dist-info/top_level.txt
jaane-0.1.1.dist-info/RECORD
