Metadata-Version: 2.4
Name: jaane
Version: 0.1.1
Summary: A simple Python package.
Author-email: Janeshvar Sivakumar <janeshvar2210182@ssn.edu.in>
License: MIT License
Classifier: Programming Language :: Python :: 3
Classifier: License :: OSI Approved :: MIT License
Classifier: Operating System :: OS Independent
Requires-Python: >=3.7
License-File: LICENCE
Provides-Extra: dev
Requires-Dist: pytest; extra == "dev"
Dynamic: license-file
